LICENSE.txt
README.md
setup.cfg
setup.py
sinyal/__init__.py
sinyal.egg-info/PKG-INFO
sinyal.egg-info/SOURCES.txt
sinyal.egg-info/dependency_links.txt
sinyal.egg-info/not-zip-safe
sinyal.egg-info/top_level.txt