Metadata-Version: 2.1
Name: sinyal
Version: 0.0.1
Summary: A library for processing and analysing physiological
Home-page: http://github.com/faruqsandi/sinyal
Author: Faruq Sandi
Author-email: faruqsandi@gmail.com
License: MIT
Platform: UNKNOWN
License-File: LICENSE.txt
